odoo/addons/letsencrypt/README.rst
odoo/addons/letsencrypt/__init__.py
odoo/addons/letsencrypt/__manifest__.py
odoo/addons/letsencrypt/hooks.py
odoo/addons/letsencrypt/controllers/__init__.py
odoo/addons/letsencrypt/controllers/main.py
odoo/addons/letsencrypt/data/ir_config_parameter.xml
odoo/addons/letsencrypt/data/ir_cron.xml
odoo/addons/letsencrypt/demo/ir_cron.xml
odoo/addons/letsencrypt/i18n/am.po
odoo/addons/letsencrypt/i18n/ar.po
odoo/addons/letsencrypt/i18n/bg.po
odoo/addons/letsencrypt/i18n/bs.po
odoo/addons/letsencrypt/i18n/ca.po
odoo/addons/letsencrypt/i18n/cs.po
odoo/addons/letsencrypt/i18n/da.po
odoo/addons/letsencrypt/i18n/de.po
odoo/addons/letsencrypt/i18n/el_GR.po
odoo/addons/letsencrypt/i18n/en_GB.po
odoo/addons/letsencrypt/i18n/es.po
odoo/addons/letsencrypt/i18n/es_AR.po
odoo/addons/letsencrypt/i18n/es_CL.po
odoo/addons/letsencrypt/i18n/es_CO.po
odoo/addons/letsencrypt/i18n/es_CR.po
odoo/addons/letsencrypt/i18n/es_DO.po
odoo/addons/letsencrypt/i18n/es_EC.po
odoo/addons/letsencrypt/i18n/es_ES.po
odoo/addons/letsencrypt/i18n/es_MX.po
odoo/addons/letsencrypt/i18n/es_PE.po
odoo/addons/letsencrypt/i18n/es_PY.po
odoo/addons/letsencrypt/i18n/es_VE.po
odoo/addons/letsencrypt/i18n/et.po
odoo/addons/letsencrypt/i18n/eu.po
odoo/addons/letsencrypt/i18n/fa.po
odoo/addons/letsencrypt/i18n/fi.po
odoo/addons/letsencrypt/i18n/fr.po
odoo/addons/letsencrypt/i18n/fr_CA.po
odoo/addons/letsencrypt/i18n/fr_CH.po
odoo/addons/letsencrypt/i18n/gl.po
odoo/addons/letsencrypt/i18n/gl_ES.po
odoo/addons/letsencrypt/i18n/he.po
odoo/addons/letsencrypt/i18n/hr.po
odoo/addons/letsencrypt/i18n/hr_HR.po
odoo/addons/letsencrypt/i18n/hu.po
odoo/addons/letsencrypt/i18n/id.po
odoo/addons/letsencrypt/i18n/it.po
odoo/addons/letsencrypt/i18n/ja.po
odoo/addons/letsencrypt/i18n/ko.po
odoo/addons/letsencrypt/i18n/letsencrypt.pot
odoo/addons/letsencrypt/i18n/lt.po
odoo/addons/letsencrypt/i18n/lt_LT.po
odoo/addons/letsencrypt/i18n/lv.po
odoo/addons/letsencrypt/i18n/mk.po
odoo_addon_letsencrypt-16.0.1.1.1.1.dist-info/METADATA
odoo_addon_letsencrypt-16.0.1.1.1.1.dist-info/WHEEL
odoo_addon_letsencrypt-16.0.1.1.1.1.dist-info/top_level.txt
odoo_addon_letsencrypt-16.0.1.1.1.1.dist-info/RECORD
