Metadata-Version: 2.1
Name: odoo-addon-letsencrypt
Version: 16.0.1.1.1.1
Summary: Request SSL certificates from letsencrypt.org
Home-page: https://github.com/OCA/server-tools
Author: Therp BV,Tecnativa,Acysos S.L,Odoo Community Association (OCA)
Author-email: support@odoo-community.org
License: AGPL-3
Classifier: Programming Language :: Python
Classifier: Framework :: Odoo
Classifier: Framework :: Odoo :: 16.0
Classifier: License :: OSI Approved :: GNU Affero General Public License v3
Requires-Python: >=3.10
Requires-Dist: acme
Requires-Dist: dnspython
Requires-Dist: josepy
Requires-Dist: odoo<16.1dev,>=16.0a
